{"symbols":{"WinstonLogger":{"hasNamespace":false,"type":0,"moduleName":"WinstonLogger","relativePath":"lib\\WinstonLogger"},"LoggerStream":{"hasNamespace":false,"type":0,"moduleName":"LoggerStream","relativePath":"src\\Logging\\LoggerStream"},"Morgan":{"hasNamespace":false,"type":0,"moduleName":"Morgan","relativePath":"lib\\logging\\Morgan"},"IUser":{"hasNamespace":false,"type":1,"moduleName":"Interfaces","relativePath":"src\\Interfaces"},"IStreak":{"hasNamespace":false,"type":1,"moduleName":"Interfaces","relativePath":"src\\Interfaces"},"IFixedTermStreak":{"hasNamespace":false,"type":1,"moduleName":"Interfaces","relativePath":"src\\Interfaces"},"ILastManStandingStreak":{"hasNamespace":false,"type":1,"moduleName":"Interfaces","relativePath":"src\\Interfaces"},"Auth":{"hasNamespace":false,"type":0,"moduleName":"Authentication","relativePath":"lib\\Authentication"},"Logger":{"hasNamespace":false,"type":0,"moduleName":"Logger","relativePath":"src\\Logging\\Logger"},"MockedRequest":{"hasNamespace":false,"type":1,"moduleName":"mockRequest","relativePath":"src\\test\\mockRequest"},"DatabaseHelper":{"hasNamespace":false,"type":0,"moduleName":"databaseHelper","relativePath":"src\\Utils\\databaseHelper"},"UserRoutes":{"hasNamespace":false,"type":0,"moduleName":"user.routes","relativePath":"src\\Routes\\user.routes"},"ErrorMessageHelper":{"hasNamespace":false,"type":0,"moduleName":"errorMessage.helper","relativePath":"src\\Utils\\errorMessage.helper"},"App":{"hasNamespace":false,"type":0,"moduleName":"app","relativePath":"src\\app"},"UserRouter":{"hasNamespace":false,"type":0,"moduleName":"user","relativePath":"src\\Logic\\User\\user"},"StreakRouter":{"hasNamespace":false,"type":0,"moduleName":"streak","relativePath":"src\\Logic\\Streak\\streak"},"UserUtils":{"hasNamespace":false,"type":0,"moduleName":"user.utils","relativePath":"src\\Middleware\\user.utils"},"PasswordHelper":{"hasNamespace":false,"type":0,"moduleName":"passsord.helper","relativePath":"src\\Middleware\\passsord.helper"},"UserValidationMiddleware":{"hasNamespace":false,"type":0,"moduleName":"user.validation.middleware","relativePath":"src\\Middleware\\user.validation.middleware"},"Routes":{"hasNamespace":false,"type":0,"moduleName":"routes","relativePath":"src\\Routes\\routes"}},"files":{"lib\\app.ts":"2018-11-10T07:14:13.991Z","lib\\Authentication.ts":"2018-11-09T07:19:04.279Z","lib\\Interfaces.ts":"2018-11-07T07:46:44.288Z","lib\\route.ts":"2018-11-10T07:15:10.669Z","lib\\server.ts":"2018-11-09T07:13:32.907Z","tests\\routes.ts":"2018-10-01T06:30:25.253Z","tests\\streak.get.test.ts":"2018-10-17T06:33:53.327Z","tests\\streak.post.test.ts":"2018-10-17T06:31:57.549Z","tests\\test-data.ts":"2018-09-13T19:38:18.325Z","tests\\TestEnums.ts":"2018-09-07T05:57:01.268Z","tests\\user.get.test.ts":"2018-10-17T06:37:07.585Z","tests\\user.login.test.ts":"2018-09-07T06:44:40.207Z","tests\\user.post.test.ts":"2018-10-17T06:37:36.511Z","lib\\models\\Streak.ts":"2018-10-17T06:34:31.412Z","lib\\models\\User.ts":"2018-11-07T07:45:47.230Z","lib\\logging\\Logger.ts":"2018-11-09T07:23:45.611Z","lib\\logging\\LoggerStream.ts":"2018-10-27T19:31:59.766Z","config\\ENVIRONMENT_CONFIG.ts":"2018-10-26T06:38:42.154Z","config\\DATABASE_CONFIG.ts":"2018-10-26T06:30:32.527Z","lib\\routes\\User\\user.validation.ts":"2018-11-10T07:16:23.703Z","lib\\routes\\Streak\\streak.ts":"2018-11-09T07:23:20.826Z","lib\\routes\\User\\user.ts":"2018-11-09T07:23:01.231Z","lib\\validation.ts":"2018-11-10T07:11:15.101Z","src\\test\\mockRequest.ts":"2018-11-11T08:02:33.378Z","src\\routes\\User\\user.ts":"2018-11-16T07:11:35.013Z","src\\app.ts":"2018-12-06T21:44:57.068Z","config\\passport.ts":"2018-11-16T07:29:17.176Z","src\\Interfaces.ts":"2018-11-07T07:46:44.288Z","src\\server.ts":"2018-12-06T21:42:21.704Z","src\\validation.ts":"2018-11-10T07:11:15.101Z","src\\logging\\Logger.ts":"2018-11-09T07:23:45.611Z","src\\logging\\LoggerStream.ts":"2018-10-27T19:31:59.766Z","src\\models\\Streak.ts":"2018-10-17T06:34:31.412Z","src\\models\\User.ts":"2018-11-07T07:45:47.230Z","src\\routes\\Streak\\streak.ts":"2018-11-09T07:23:20.826Z","src\\Logging\\Logger.ts":"2018-11-09T07:23:45.611Z","src\\Logging\\LoggerStream.ts":"2018-10-27T19:31:59.766Z","src\\Models\\Streak.ts":"2018-10-17T06:34:31.412Z","src\\Models\\User.ts":"2018-12-12T07:09:37.775Z","src\\Validation\\user.validation.ts":"2018-11-16T07:10:46.669Z","src\\Logic\\Streak\\streak.ts":"2018-12-06T21:45:35.310Z","src\\Logic\\User\\user.ts":"2018-12-06T21:45:27.421Z","src\\Routes\\routes.ts":"2018-12-17T07:25:55.143Z","src\\Utils\\errorMessage.helper.ts":"2018-11-18T07:42:48.180Z","src\\tests\\Middleware\\user.validation.middleware.test.ts":"2018-11-23T07:17:41.688Z","src\\tests\\Utils\\errorMessager.helper.test.ts":"2018-11-23T07:18:24.766Z","src\\tests\\Validation\\user.validation.test.ts":"2018-11-23T07:18:08.173Z","src\\tests\\Utils\\user.utils.test.ts":"2018-11-23T07:18:24.774Z","src\\tests\\Utils\\password.helper.test.ts":"2018-11-23T07:18:24.766Z","src\\unit-tests\\Middleware\\user.validation.middleware.test.ts":"2018-11-30T06:41:53.760Z","src\\unit-tests\\Utils\\password.helper.test.ts":"2018-11-24T09:39:07.362Z","unit-tests\\Middleware\\user.validation.middleware.test.ts":"2018-11-24T09:45:21.297Z","unit-tests\\Validation\\user.validation.test.ts":"2018-11-24T09:45:06.749Z","unit-tests\\Utils\\errorMessager.helper.test.ts":"2018-11-24T09:45:21.273Z","unit-tests\\Utils\\password.helper.test.ts":"2018-11-24T09:46:08.636Z","unit-tests\\Utils\\user.utils.test.ts":"2018-11-24T09:44:59.850Z","tests\\unit\\Utils\\errorMessager.helper.test.ts":"2018-12-05T07:33:38.052Z","tests\\unit\\Validation\\user.validation.test.ts":"2018-12-06T21:46:02.276Z","src\\Middleware\\user.utils.ts":"2018-12-09T07:39:19.587Z","tests\\unit\\Middleware\\user.utils.test.ts":"2018-12-05T07:25:28.721Z","src\\Middleware\\passsord.helper.ts":"2018-12-09T07:48:12.659Z","tests\\unit\\Middleware\\password.helper.test.ts":"2018-12-10T07:20:48.531Z","src\\Middleware\\Database\\doesEmailExist.ts":"2018-12-17T06:53:13.945Z","tests\\unit\\Middleware\\Database\\doesEmailExist.test.ts":"2018-12-17T07:04:27.391Z","src\\Middleware\\Validation\\emailExistsValidation.ts":"2018-12-17T07:24:49.036Z","tests\\unit\\Middleware\\Validation\\emailExistsValidation.test.ts":"2018-12-12T07:52:31.981Z","src\\Middleware\\Database\\doesUserNameExist.ts":"2018-12-17T06:59:04.975Z","tests\\unit\\Middleware\\Database\\doesUserNameExist.test.ts":"2018-12-17T07:02:48.324Z","tests\\unit\\Middleware\\Database\\saveUserToDatabase.test.ts":"2018-12-17T07:21:56.421Z","src\\Middleware\\Database\\saveUserToDatabase.ts":"2018-12-17T07:32:47.564Z","src\\Middleware\\Validation\\userNameExistsValidation.ts":"2018-12-17T07:28:31.911Z","tests\\unit\\Middleware\\Validation\\userNameExistsValidation.test.ts":"2018-12-17T07:36:05.626Z"}}